llano/__init__.py
llano/config.py
llano/utils.py
llano/annotators/__init__.py
llano/annotators/base.py
llano/annotators/gpt.py
llano/models/__init__.py
llano/models/base.py
llano/models/gpt.py
llano/templates/texts/classification.en.jinja
llano/templates/texts/classification.zh_cn.jinja
llano/templates/texts/data_augmentation.en.jinja
llano/templates/texts/data_augmentation.zh_cn.jinja
llano/templates/texts/multilabel_classification.en.jinja
llano/templates/texts/multilabel_classification.zh_cn.jinja
llano/templates/texts/ner.en.jinja
llano/templates/texts/ner.zh_cn.jinja
llano/templates/texts/relation_extraction.en.jinja
llano/templates/texts/relation_extraction.zh_cn.jinja
llano-0.1.8.dist-info/LICENSE
llano-0.1.8.dist-info/METADATA
llano-0.1.8.dist-info/WHEEL
llano-0.1.8.dist-info/top_level.txt
llano-0.1.8.dist-info/RECORD
