Metadata-Version: 2.1
Name: llano
Version: 0.1.8
Summary: Let Large Language Models Serve As Data Annotators.
Home-page: https://github.com/SeanLee97/llano
Author: sean lee
Author-email: xmlee97@gmail.com
License: Apache 2.0 License
Keywords: LLM,NLP,Annotator,Prompt
Platform: all
Classifier: Intended Audience :: Developers
Classifier: Operating System :: OS Independent
Classifier: License :: OSI Approved :: MIT License
Classifier: Programming Language :: Python
Classifier: Programming Language :: Python :: 3
Classifier: Programming Language :: Python :: 3.8
Classifier: Programming Language :: Python :: 3.9
Classifier: Programming Language :: Python :: 3.10
Classifier: Topic :: Text Processing
Classifier: Topic :: Text Processing :: Indexing
Classifier: Topic :: Text Processing :: Linguistic
License-File: LICENSE
Requires-Dist: Jinja2 (>=3.0.3)
Requires-Dist: openai (>=0.27.0)
Requires-Dist: tiktoken (>=0.3.0)
